monzo/__init__.py
monzo/auth.py
monzo/errors.py
monzo/monzo.py
monzo-test/__init__.py
monzo-test/auth.py
monzo-test/errors.py
monzo-test/monzo.py
monzo_test-0.6.1.dist-info/METADATA
monzo_test-0.6.1.dist-info/RECORD
monzo_test-0.6.1.dist-info/WHEEL
monzo_test-0.6.1.dist-info/top_level.txt
